jc/__init__.py
jc/__main__.py
jc/appdirs.py
jc/cli.py
jc/cli_data.py
jc/exceptions.py
jc/jc_types.py
jc/lib.py
jc/py.typed
jc/shell_completions.py
jc/streaming.py
jc/tracebackplus.py
jc/utils.py
jc/parsers/__init__.py
jc/parsers/acpi.py
jc/parsers/airport.py
jc/parsers/airport_s.py
jc/parsers/amixer.py
jc/parsers/apt_cache_show.py
jc/parsers/apt_get_sqq.py
jc/parsers/arp.py
jc/parsers/asciitable.py
jc/parsers/asciitable_m.py
jc/parsers/blkid.py
jc/parsers/bluetoothctl.py
jc/parsers/broken_parser.py
jc/parsers/cbt.py
jc/parsers/cef.py
jc/parsers/cef_s.py
jc/parsers/certbot.py
jc/parsers/chage.py
jc/parsers/cksum.py
jc/parsers/clf.py
jc/parsers/clf_s.py
jc/parsers/crontab.py
jc/parsers/crontab_u.py
jc/parsers/csv.py
jc/parsers/csv_s.py
jc/parsers/curl_head.py
jc/parsers/date.py
jc/parsers/datetime_iso.py
jc/parsers/debconf_show.py
jc/parsers/df.py
jc/parsers/dig.py
jc/parsers/dir.py
jc/parsers/disabled_parser.py
jc/parsers/dmidecode.py
jc/parsers/dpkg_l.py
jc/parsers/du.py
jc/parsers/efibootmgr.py
jc/parsers/email_address.py
jc/parsers/env.py
jc/parsers/ethtool.py
jc/parsers/file.py
jc/parsers/find.py
jc/parsers/findmnt.py
jc/parsers/finger.py
jc/parsers/foo.py
jc/parsers/foo_s.py
jc/parsers/free.py
jc/parsers/fstab.py
jc/parsers/git_log.py
jc/parsers/git_log_s.py
jc/parsers/git_ls_remote.py
jc/parsers/gpg.py
jc/parsers/group.py
jc/parsers/gshadow.py
jc/parsers/hash.py
jc/parsers/hashsum.py
jc/parsers/hciconfig.py
jc/parsers/history.py
jc/parsers/host.py
jc/parsers/hosts.py
jc/parsers/http_headers.py
jc/parsers/id.py
jc/parsers/ifconfig.py
jc/parsers/iftop.py
jc/parsers/ini.py
jc/parsers/ini_dup.py
jc/parsers/iostat.py
jc/parsers/iostat_s.py
jc/parsers/ip_address.py
jc/parsers/ip_route.py
jc/parsers/ipconfig.py
jc/parsers/iptables.py
jc/parsers/iw_scan.py
jc/parsers/iwconfig.py
jc/parsers/jar_manifest.py
jc/parsers/jobs.py
jc/parsers/jwt.py
jc/parsers/kv.py
jc/parsers/kv_dup.py
jc/parsers/last.py
jc/parsers/ls.py
jc/parsers/ls_s.py
jc/parsers/lsattr.py
jc-1.25.6.dist-info/LICENSE.md
jc-1.25.6.dist-info/METADATA
jc-1.25.6.dist-info/WHEEL
jc-1.25.6.dist-info/entry_points.txt
jc-1.25.6.dist-info/top_level.txt
jc-1.25.6.dist-info/RECORD
