Metadata-Version: 2.1
Name: jc
Version: 1.25.6
Summary: Converts the output of popular command-line tools and file-types to JSON.
Home-page: https://github.com/kellyjonbrazil/jc
Author: Kelly Brazil
Author-email: kellyjonbrazil@gmail.com
License: MIT
Classifier: Programming Language :: Python :: 3
Classifier: License :: OSI Approved :: MIT License
Classifier: Operating System :: OS Independent
Classifier: Topic :: Utilities
Requires-Python: >=3.6
License-File: LICENSE.md
Requires-Dist: ruamel.yaml >=0.15.0
Requires-Dist: xmltodict >=0.12.0
Requires-Dist: Pygments >=2.3.0
